[["489710589166223360",{"mid":"489710589166223360","uid":"486759404750897154","content":"We are implementing a bot that will let you post to the forums via discord, but first we want to guage where it will be most used through the poll below! Please let us know your opinion 😃","stamp":1536826502840,"attach":null,"day":17787,"edited":false}],["489710613941977094",{"mid":"489710613941977094","uid":"486759404750897154","content":"-help","stamp":1536826508747,"attach":null,"day":17787,"edited":false}],["489711210191781888",{"mid":"489711210191781888","uid":"486759404750897154","content":"-callvote What section of the forum would you like to post to via discord? | What section of the forum would you like to post to via discord?  | 12h | Bragging | Methods | Other","stamp":1536826650904,"attach":null,"day":17787,"edited":false}],["489710589166223360",{"mid":"489710589166223360","uid":"486759404750897154","content":"We are implementing a bot that will let you post to the forums via discord, but first we want to guage where it will be most used through the poll below! Please let us know your opinion 😃 @everyone","stamp":1536826502840,"attach":null,"day":17787,"edited":true}],["489797611780440065",{"mid":"489797611780440065","uid":"486759404750897154","content":"We hit 400 users!!!","stamp":1536847250648,"attach":null,"day":17787,"edited":false}],["490542242898116609",{"mid":"490542242898116609","uid":"486759404750897154","content":"","stamp":1537024784541,"attach":null,"day":17789,"edited":false}],["490542331771224078",{"mid":"490542331771224078","uid":"486759404750897154","content":"","stamp":1537024805730,"attach":null,"day":17789,"edited":false}],["490542414235435010",{"mid":"490542414235435010","uid":"479794626945875987","content":"<:GWcorbinMonkaGIGA:384871327292588054>","stamp":1537024825391,"attach":null,"day":17789,"edited":false}],["490542331771224078",{"mid":"490542331771224078","uid":"486759404750897154","content":"We hit 420 users @everyone 😎","stamp":1537024805730,"attach":null,"day":17789,"edited":true}],["490547516459450368",{"mid":"490547516459450368","uid":"480571110732333077","content":"weed lol","stamp":1537026041856,"attach":null,"day":17789,"edited":false}],["490547647342444545",{"mid":"490547647342444545","uid":"133518904319410176","content":"Blaze IT","stamp":1537026073061,"attach":null,"day":17789,"edited":false}],["490831643594981386",{"mid":"490831643594981386","uid":"486759404750897154","content":"Added space invaders to the arcade! @everyone https://imperials.io/games.php?action=play&gid=4","stamp":1537093783044,"attach":null,"day":17790,"edited":false}],["490903177324134421",{"mid":"490903177324134421","uid":"479794626945875987","content":"@everyone \n**Need a platform to buy or sell  SE'd stuff / services? Join Now!!**\n\n__Website: https://secenter.xyz/__\n\nhttps://discord.gg/FT3HFSx","stamp":1537110838014,"attach":null,"day":17790,"edited":false}],["491227000002838550",{"mid":"491227000002838550","uid":"479794626945875987","content":"@everyone  \n\n**Member exclusive giveaways worth 2k-4k products comming soon.**\n\n*Requirements :- \n\nShould be a Member of Imperials.io \n\nShould have at least 2 posts\n\nShould be an active member of the community*","stamp":1537188043357,"attach":null,"day":17791,"edited":false}],["491227000002838550",{"mid":"491227000002838550","uid":"479794626945875987","content":"@everyone  \n\n**Member exclusive giveaways worth 2k-4k products coming soon.**\n\n*Requirements :- \n\nShould be a Member of Imperials.io \n\nShould have at least 2 posts\n\nShould be an active member of the community*","stamp":1537188043357,"attach":null,"day":17791,"edited":true}]]