[["495779771784101898",{"mid":"495779771784101898","uid":"204774677921398785","content":"Please make it so we can type in a start value for the bruteforcer, the slider even if you do 1 tick at a time will go up by 1000's on a big combo 😂","stamp":1538273508736,"attach":null,"day":17804,"edited":false}],["495925482626482206",{"mid":"495925482626482206","uid":"364367795351191555","content":"<@455935652207263744> i think this is for you","stamp":1538308248908,"attach":null,"day":17804,"edited":false}],["495929658139738152",{"mid":"495929658139738152","uid":"455935652207263744","content":"You can click on the sides of the slider to make it go +1/-1","stamp":1538309244428,"attach":null,"day":17804,"edited":false}],["495929816353079296",{"mid":"495929816353079296","uid":"455935652207263744","content":"Keep the mouse click down to do it quickly","stamp":1538309282149,"attach":null,"day":17804,"edited":false}]]